polygeohash/__init__.py
polygeohash/polygeohash.py
polygeohash-0.2.dist-info/DESCRIPTION.rst
polygeohash-0.2.dist-info/METADATA
polygeohash-0.2.dist-info/RECORD
polygeohash-0.2.dist-info/WHEEL
polygeohash-0.2.dist-info/metadata.json
polygeohash-0.2.dist-info/top_level.txt
